nesterlists/__init__.py
nesterlists/nesterlists.py
nesterlists-1.0.0.dist-info/LICENSE
nesterlists-1.0.0.dist-info/METADATA
nesterlists-1.0.0.dist-info/WHEEL
nesterlists-1.0.0.dist-info/top_level.txt
nesterlists-1.0.0.dist-info/RECORD
