Metadata-Version: 2.1
Name: nesterlists
Version: 1.0.0
Summary: Returns items in lists that may or may not include nested lists.
Home-page: https://github.com/Marciodm
Author: Marciodm
Author-email: marcio0770@gmail.com
License: MIT License
Platform: UNKNOWN
Classifier: Programming Language :: Python :: 3.7
Classifier: License :: OSI Approved :: MIT License
Classifier: Natural Language :: English
